codeauth_sdk/__init__.py
codeauth_sdk-1.2.1.dist-info/METADATA
codeauth_sdk-1.2.1.dist-info/WHEEL
codeauth_sdk-1.2.1.dist-info/top_level.txt
codeauth_sdk-1.2.1.dist-info/RECORD
