Metadata-Version: 2.4
Name: codeauth_sdk
Version: 1.2.1
Summary: Official Python SDK for CodeAuth
Home-page: https://codeauth.com
Author: CodeAuth
License: APACHE 2.0
Classifier: Programming Language :: Python :: 3
Classifier: License :: OSI Approved :: Apache Software License
Classifier: Operating System :: OS Independent
Dynamic: author
Dynamic: classifier
Dynamic: description
Dynamic: description-content-type
Dynamic: home-page
Dynamic: license
Dynamic: summary
